tell_a_vision/__init__.py
tell_a_vision/main.py
tell_a_vision/narrator.py
tell_a_vision/ruler.py
tell_a_vision-0.1.7.dist-info/METADATA
tell_a_vision-0.1.7.dist-info/WHEEL
tell_a_vision-0.1.7.dist-info/top_level.txt
tell_a_vision-0.1.7.dist-info/RECORD
