Metadata-Version: 2.1
Name: tell-a-vision
Version: 0.1.7
Summary: TV (tell_a_vision) is an inference engine for object detection that provides explanatory analysis for such tasks in computer vision.
Home-page: https://github.com/rezmansouri/tell_a_vision
Author: Reza Mansouri
Author-email: std_reza_mansouri@khu.ac.ir
License: MIT
Requires-Dist: numpy (>=1.21.0)
Requires-Dist: gTTs (>=2.2.4)
